itkwasm_mesh_io_emscripten/__init__.py
itkwasm_mesh_io_emscripten/_version.py
itkwasm_mesh_io_emscripten/byu_read_mesh_async.py
itkwasm_mesh_io_emscripten/byu_write_mesh_async.py
itkwasm_mesh_io_emscripten/extension_to_mesh_io.py
itkwasm_mesh_io_emscripten/extension_to_point_set_io.py
itkwasm_mesh_io_emscripten/free_surfer_ascii_read_mesh_async.py
itkwasm_mesh_io_emscripten/free_surfer_ascii_write_mesh_async.py
itkwasm_mesh_io_emscripten/free_surfer_binary_read_mesh_async.py
itkwasm_mesh_io_emscripten/free_surfer_binary_write_mesh_async.py
itkwasm_mesh_io_emscripten/js_package.py
itkwasm_mesh_io_emscripten/mesh_io_index.py
itkwasm_mesh_io_emscripten/mz3_read_mesh_async.py
itkwasm_mesh_io_emscripten/mz3_read_point_set_async.py
itkwasm_mesh_io_emscripten/mz3_write_mesh_async.py
itkwasm_mesh_io_emscripten/mz3_write_point_set_async.py
itkwasm_mesh_io_emscripten/obj_read_mesh_async.py
itkwasm_mesh_io_emscripten/obj_read_point_set_async.py
itkwasm_mesh_io_emscripten/obj_write_mesh_async.py
itkwasm_mesh_io_emscripten/obj_write_point_set_async.py
itkwasm_mesh_io_emscripten/off_read_mesh_async.py
itkwasm_mesh_io_emscripten/off_read_point_set_async.py
itkwasm_mesh_io_emscripten/off_write_mesh_async.py
itkwasm_mesh_io_emscripten/off_write_point_set_async.py
itkwasm_mesh_io_emscripten/point_set_io_index.py
itkwasm_mesh_io_emscripten/read_mesh_async.py
itkwasm_mesh_io_emscripten/read_point_set_async.py
itkwasm_mesh_io_emscripten/stl_read_mesh_async.py
itkwasm_mesh_io_emscripten/stl_write_mesh_async.py
itkwasm_mesh_io_emscripten/swc_read_mesh_async.py
itkwasm_mesh_io_emscripten/swc_write_mesh_async.py
itkwasm_mesh_io_emscripten/vtk_poly_data_read_mesh_async.py
itkwasm_mesh_io_emscripten/vtk_poly_data_read_point_set_async.py
itkwasm_mesh_io_emscripten/vtk_poly_data_write_mesh_async.py
itkwasm_mesh_io_emscripten/vtk_poly_data_write_point_set_async.py
itkwasm_mesh_io_emscripten/wasm_read_mesh_async.py
itkwasm_mesh_io_emscripten/wasm_read_point_set_async.py
itkwasm_mesh_io_emscripten-1.7.1.dist-info/METADATA
itkwasm_mesh_io_emscripten-1.7.1.dist-info/WHEEL
itkwasm_mesh_io_emscripten-1.7.1.dist-info/RECORD
